webgenesis/__init__.py
webgenesis/webgenesis.py
webgenesis-0.0.1.dist-info/entry_points.txt
webgenesis-0.0.1.dist-info/WHEEL
webgenesis-0.0.1.dist-info/METADATA
webgenesis-0.0.1.dist-info/RECORD
