Metadata-Version: 2.1
Name: webgenesis
Version: 0.0.1
Summary: create basic hello-world apps for the various web frameworks as boiler plates
Home-page: https://github.com/jcharistech/webgenesis
License: MIT
Keywords: webgenesis,webkit,cookiecutter,jcharistech,web microframeworks,flask,hello world app,streamlit
Author: Jesse E.Agbe(JCharis)
Author-email: jcharistech@gmail.com
Requires-Python: >=3.8,<4.0
Classifier: License :: OSI Approved :: MIT License
Classifier: Operating System :: OS Independent
Classifier: Programming Language :: Python :: 3
Classifier: Programming Language :: Python :: 3.6
Classifier: Programming Language :: Python :: 3.7
Classifier: Programming Language :: Python :: 3.8
Classifier: Programming Language :: Python :: 3.9
Requires-Dist: click (>=8.0.1,<9.0.0)
Project-URL: Repository, https://github.com/jcharistech/webgenesis
